cvss_converter/__init__.py
cvss_converter/converter/__init__.py
cvss_converter/converter/converter.py
cvss_converter/tests/__init__.py
cvss_converter/tests/test_converter.py
tests/__init__.py
tests/test_converter.py
cvss_converter-0.1.4.dist-info/LICENSE
cvss_converter-0.1.4.dist-info/METADATA
cvss_converter-0.1.4.dist-info/WHEEL
cvss_converter-0.1.4.dist-info/top_level.txt
cvss_converter-0.1.4.dist-info/RECORD
