Metadata-Version: 2.1
Name: cvss_converter
Version: 0.1.4
Summary: A package to convert CVSSv2 to CVSSv3
Home-page: https://github.com/SECTA5/cvss-converter
Author: SECTA5
Author-email: hidden@secta5.com
Classifier: Programming Language :: Python :: 3
Classifier: License :: OSI Approved :: MIT License
Classifier: Operating System :: OS Independent
Requires-Python: >=3.6
License-File: LICENSE
Requires-Dist: cvss
Provides-Extra: dev
Requires-Dist: pytest ; extra == 'dev'
